setup.cfg
setup.py
src/mock_utils/__init__.py
src/mock_utils/mock_file.py
src/mock_utils.egg-info/PKG-INFO
src/mock_utils.egg-info/SOURCES.txt
src/mock_utils.egg-info/dependency_links.txt
src/mock_utils.egg-info/top_level.txt
src/mock_utils/tests/__init__.py
src/mock_utils/tests/mock_file_test.py