Metadata-Version: 1.1
Name: mock-utils
Version: 0.4.1
Summary: Python package providing utilities for mocking stuff on Python.
Home-page: https://gitlab.com/tarcisioe/mock_utils
Author: Tarcísio Eduardo Moreira Crocomo
Author-email: tarcisio.crocomo+pypi@gmail.com
License: UNKNOWN
Download-URL: https://gitlab.com/tarcisioe/mock_utils/repository/archive.tar.gz?ref=0.4.1
Keywords: testing,mock,file
Platform: UNKNOWN
